odoo/addons/stock_picking_auto_print/README.rst
odoo/addons/stock_picking_auto_print/__init__.py
odoo/addons/stock_picking_auto_print/__manifest__.py
odoo/addons/stock_picking_auto_print/i18n/stock_picking_auto_print.pot
odoo/addons/stock_picking_auto_print/models/__init__.py
odoo/addons/stock_picking_auto_print/models/stock_picking.py
odoo/addons/stock_picking_auto_print/models/stock_picking_type.py
odoo/addons/stock_picking_auto_print/readme/CONTRIBUTORS.rst
odoo/addons/stock_picking_auto_print/readme/DESCRIPTION.rst
odoo/addons/stock_picking_auto_print/static/description/icon.png
odoo/addons/stock_picking_auto_print/static/description/index.html
odoo/addons/stock_picking_auto_print/tests/__init__.py
odoo/addons/stock_picking_auto_print/tests/common.py
odoo/addons/stock_picking_auto_print/tests/test_stock_picking_auto_print.py
odoo/addons/stock_picking_auto_print/views/stock_picking_type_views.xml
odoo_addon_stock_picking_auto_print-15.0.1.0.0.2.dist-info/METADATA
odoo_addon_stock_picking_auto_print-15.0.1.0.0.2.dist-info/WHEEL
odoo_addon_stock_picking_auto_print-15.0.1.0.0.2.dist-info/top_level.txt
odoo_addon_stock_picking_auto_print-15.0.1.0.0.2.dist-info/RECORD
