Metadata-Version: 2.1
Name: odoo-addon-stock_picking_auto_print
Version: 15.0.1.0.0.2
Summary: Print picking delivery slip automatically after validation
Home-page: https://github.com/OCA/stock-logistics-reporting
Author: Tecnativa, Odoo Community Association (OCA)
Author-email: support@odoo-community.org
License: AGPL-3
Classifier: Programming Language :: Python
Classifier: Framework :: Odoo
Classifier: Framework :: Odoo :: 15.0
Classifier: License :: OSI Approved :: GNU Affero General Public License v3
Requires-Python: >=3.8
Requires-Dist: odoo-addon-web-ir-actions-act-multi<15.1dev,>=15.0dev
Requires-Dist: odoo<15.1dev,>=15.0a
